{"name":"Title of your scenario","id":"title-of-your-feature;title-of-your-scenario","testSteps":[{"number":1,"description":"Given that Juan needs to create an employe in OrageHR","duration":18198,"startTime":"2018-09-20T13:15:19.887-05:00[America/Bogota]","screenshots":[{"screenshot":"98b5ce3b1d0cf8c05bd9d15ca1a37e0d53a14a851798b0d334ae627716349d3f.png"}],"result":"SUCCESS","precondition":false,"children":[{"number":2,"description":"Juan opens the Orange hrm","duration":12678,"startTime":"2018-09-20T13:15:20.300-05:00[America/Bogota]","screenshots":[{"screenshot":"6e5fe074f3c05fc86b9efe6942714eb99749e26ca2e2bf237bfc72ba60d618df.png"}],"result":"SUCCESS","precondition":false},{"number":3,"description":"Juan clicks on log in buttong","duration":4718,"startTime":"2018-09-20T13:15:32.994-05:00[America/Bogota]","screenshots":[{"screenshot":"5fbe58393ff6aff8f693f44792cc9173a2ab1f4cbf617c8ad5f39445295382a1.png"}],"result":"SUCCESS","precondition":false}]},{"number":4,"description":"When he performs the entry of the record in the application\r\n| Option | firstName | middleName | lastName | employeId | location | userName | status | password | confirmPassword | adminRole | titlePopUp |\r\n| PIM | peityn | tiendyn | peityn | 0444 | Australian Regional HQ | 1pepito24 | Disabled | 3158985879Ss | 3158985879Ss | Global Admin | Add Employee |","duration":36346,"startTime":"2018-09-20T13:15:38.086-05:00[America/Bogota]","screenshots":[{"screenshot":"66a4611f8ddf69bbd0c367100a7314ed73b221cee9d839163947b492a87d7d16.png"}],"result":"SUCCESS","precondition":false,"children":[{"number":5,"description":"Juan clicks on add employe option","duration":1185,"startTime":"2018-09-20T13:15:39.835-05:00[America/Bogota]","screenshots":[{"screenshot":"61918f8982dc1549733d2ddd991a4e46132dbacbe885bbece1125e1492ac9193.png"}],"result":"SUCCESS","precondition":false},{"number":6,"description":"Then pop up employe should be \u0027Add Employee\u0027","duration":10407,"startTime":"2018-09-20T13:15:41.645-05:00[America/Bogota]","screenshots":[{"screenshot":"718dc7d28f7282b11eaa11d12b729ef2541e64321bf22cb80330e0bb3f76ea8c.png"}],"result":"SUCCESS","precondition":false},{"number":7,"description":"Juan enters \u0027peityn\u0027 into first name field","duration":2118,"startTime":"2018-09-20T13:15:52.076-05:00[America/Bogota]","screenshots":[{"screenshot":"549b77597af1552c4e52c13f9df060a7eee813c12ba0e17b77263f16ee7165cb.png"}],"result":"SUCCESS","precondition":false},{"number":8,"description":"Juan enters \u0027tiendyn\u0027 into middle name field","duration":930,"startTime":"2018-09-20T13:15:54.198-05:00[America/Bogota]","screenshots":[{"screenshot":"7a92bace839a2a55d67f011545a286929e90083133e1d5f02a048e90558cd6d2.png"}],"result":"SUCCESS","precondition":false},{"number":9,"description":"Juan enters \u0027peityn\u0027 into last name field","duration":878,"startTime":"2018-09-20T13:15:55.131-05:00[America/Bogota]","screenshots":[{"screenshot":"75f2c6b15c5a6a0c682c486170ecd2fb05b5bb8409c45263dc45135b76a586ae.png"}],"result":"SUCCESS","precondition":false},{"number":10,"description":"Juan enters \u00270444\u0027 into employe id field","duration":809,"startTime":"2018-09-20T13:15:56.013-05:00[America/Bogota]","screenshots":[{"screenshot":"8aed9e25e2be4ac36717a895d67486cffc5fbf0f213ff8209bd29d8b46537ae8.png"}],"result":"SUCCESS","precondition":false},{"number":11,"description":"Juan clicks on select location","duration":642,"startTime":"2018-09-20T13:15:56.825-05:00[America/Bogota]","screenshots":[{"screenshot":"f6a57dc3d9a0625d2356ad9c0465f90841be369eee22b5df3e06c66a99c080ca.png"}],"result":"SUCCESS","precondition":false},{"number":12,"description":"Juan clicks on loging credentials checkbox","duration":721,"startTime":"2018-09-20T13:15:57.811-05:00[America/Bogota]","screenshots":[{"screenshot":"ddf970e9988fbd2cd28a8cf010ec1306708880c9a0926580f2968cb00eeb39b6.png"}],"result":"SUCCESS","precondition":false},{"number":13,"description":"Juan enters \u00271pepito24\u0027 into username field","duration":926,"startTime":"2018-09-20T13:15:58.535-05:00[America/Bogota]","screenshots":[{"screenshot":"667280f4fb84438528dcc45acba0acad354abd6adbefc21e5a773cace321c6f7.png"}],"result":"SUCCESS","precondition":false},{"number":14,"description":"Juan clicks on select status","duration":575,"startTime":"2018-09-20T13:15:59.465-05:00[America/Bogota]","screenshots":[{"screenshot":"b282a548f07b3408d33837f7f39ce41821bd6386148a1378115ad23c91f7ab52.png"}],"result":"SUCCESS","precondition":false},{"number":15,"description":"Juan enters \u00273158985879Ss\u0027 into password field","duration":1136,"startTime":"2018-09-20T13:16:00.294-05:00[America/Bogota]","screenshots":[{"screenshot":"0b95f633b505219a494eb67bf5bf8f5cd8de710f4571add08e8882ceed1e34ce.png"}],"result":"SUCCESS","precondition":false},{"number":16,"description":"Juan enters \u00273158985879Ss\u0027 into confirm password field","duration":1140,"startTime":"2018-09-20T13:16:01.434-05:00[America/Bogota]","screenshots":[{"screenshot":"ea7c1e3c29be9a78061335a683a8b93b2b142df33508610e5daa745872ef932f.png"}],"result":"SUCCESS","precondition":false},{"number":17,"description":"Juan clicks on select admin role","duration":565,"startTime":"2018-09-20T13:16:02.577-05:00[America/Bogota]","screenshots":[{"screenshot":"f9d804b1ee0d3efe6b128bd6cde0e777e7f0b8f97bcd0f7c9a43043e433483f6.png"}],"result":"SUCCESS","precondition":false},{"number":18,"description":"Juan clicks on save button","duration":701,"startTime":"2018-09-20T13:16:03.397-05:00[America/Bogota]","screenshots":[{"screenshot":"8d4ba2d278bff256523a497c7f6ac53b572a773f94269c167f96bf1739fc5723.png"}],"result":"SUCCESS","precondition":false}]},{"number":19,"description":"Then he visualize the new employe in the application\r\n| Option | employeeName |\r\n| PIM | peityn tiendyn peityn |","duration":6129,"startTime":"2018-09-20T13:16:14.433-05:00[America/Bogota]","screenshots":[{"screenshot":"2de0e8db5d5e860ffa644db4b60212eebe3d8f3a1ae4e02c1bf7058377eb2676.png"}],"result":"SUCCESS","precondition":false,"children":[{"number":20,"description":"Juan clicks on Employee list field","duration":774,"startTime":"2018-09-20T13:16:14.436-05:00[America/Bogota]","screenshots":[{"screenshot":"a37233e5b8367fdef5e7c070d38082d9e18b0831dbcdefeb0fc8db6b7a218ae7.png"}],"result":"SUCCESS","precondition":false},{"number":21,"description":"Juan enters \u0027peityn tiendyn peityn\u0027 into emplyee name search field","duration":1653,"startTime":"2018-09-20T13:16:15.214-05:00[America/Bogota]","screenshots":[{"screenshot":"0b99760c9059411da01eb350731b4f5f21304507b8de830ca5f09a890d74301c.png"}],"result":"SUCCESS","precondition":false},{"number":22,"description":"Then search for should be (true)","duration":3399,"startTime":"2018-09-20T13:16:16.871-05:00[America/Bogota]","screenshots":[{"screenshot":"948964b5491854231940ae9bf1e006d8989a602bf8f1e3cd92ba4a76ac7cc595.png"}],"result":"SUCCESS","precondition":false}]}],"userStory":{"id":"title-of-your-feature","storyName":"Title of your feature","path":"src/test/resources/features/OrangeHRM.feature","narrative":"  I want to use this template for my feature file","type":"feature"},"featureTag":{"name":"Features/Title of your feature","type":"feature"},"title":"Title of your scenario","tags":[{"name":"tag","type":"tag"},{"name":"Title of your feature","type":"feature"},{"name":"SuccesfullCase","type":"tag"}],"startTime":"2018-09-20T13:15:15.729-05:00[America/Bogota]","duration":65118,"projectKey":"","sessionId":"b910bd051788b28d8ae132ab7746501e","driver":"chrome","manual":false,"testSource":"Cucumber","result":"SUCCESS"}